progron/__init__.py
progron/adapters/redis.py
progron/api/entities/enums.py
progron/api/entities/key.py
progron/api/entities/status.py
progron/api/protocols/tracker.py
progron/utils/json.py
progron-0.1.0.dist-info/LICENSE
progron-0.1.0.dist-info/METADATA
progron-0.1.0.dist-info/WHEEL
progron-0.1.0.dist-info/top_level.txt
progron-0.1.0.dist-info/RECORD
